[
  {
    "name": "Products",
    "slug": "products",
    "brandCount": 1372
  },
  {
    "name": "Accessories",
    "slug": "accessories",
    "brandCount": 323
  },
  {
    "name": "Health & Beauty",
    "slug": "health-and-beauty",
    "brandCount": 289
  },
  {
    "name": "Clothing",
    "slug": "clothing",
    "brandCount": 250
  },
  {
    "name": "Home & Garden",
    "slug": "home-and-garden",
    "brandCount": 181
  },
  {
    "name": "Electronics",
    "slug": "electronics",
    "brandCount": 154
  },
  {
    "name": "Travel & Vacations",
    "slug": "travel-and-vacations",
    "brandCount": 130
  },
  {
    "name": "Shoes",
    "slug": "shoes",
    "brandCount": 126
  },
  {
    "name": "Digital Services & Streaming",
    "slug": "digital-services-and-streaming",
    "brandCount": 124
  },
  {
    "name": "Sports, Outdoors & Fitness",
    "slug": "sports-outdoors-and-fitness",
    "brandCount": 118
  },
  {
    "name": "Food, Drinks & Restaurants",
    "slug": "food-drinks-and-restaurants",
    "brandCount": 97
  },
  {
    "name": "Auto & Tires",
    "slug": "auto-and-tires",
    "brandCount": 60
  },
  {
    "name": "Gifts, Flowers & Parties",
    "slug": "gifts-flowers-and-parties",
    "brandCount": 51
  },
  {
    "name": "Office Supplies",
    "slug": "office-supplies",
    "brandCount": 48
  },
  {
    "name": "Events & Entertainment",
    "slug": "events-and-entertainment",
    "brandCount": 45
  },
  {
    "name": "Subscription Boxes & Services",
    "slug": "subscription-boxes-and-services",
    "brandCount": 38
  },
  {
    "name": "Pets",
    "slug": "pets",
    "brandCount": 30
  },
  {
    "name": "Toys & Games",
    "slug": "toys-and-games",
    "brandCount": 30
  },
  {
    "name": "Baby & Toddler",
    "slug": "baby-and-toddler",
    "brandCount": 19
  }
]