[
  {
    "name": "Products",
    "slug": "products",
    "brandCount": 1197
  },
  {
    "name": "Travel & Vacations",
    "slug": "travel-and-vacations",
    "brandCount": 213
  },
  {
    "name": "Accessories",
    "slug": "accessories",
    "brandCount": 211
  },
  {
    "name": "Health & Beauty",
    "slug": "health-and-beauty",
    "brandCount": 208
  },
  {
    "name": "Electronics",
    "slug": "electronics",
    "brandCount": 187
  },
  {
    "name": "Home & Garden",
    "slug": "home-and-garden",
    "brandCount": 175
  },
  {
    "name": "Clothing",
    "slug": "clothing",
    "brandCount": 159
  },
  {
    "name": "Sports, Outdoors & Fitness",
    "slug": "sports-outdoors-and-fitness",
    "brandCount": 154
  },
  {
    "name": "Digital Services & Streaming",
    "slug": "digital-services-and-streaming",
    "brandCount": 146
  },
  {
    "name": "Shoes",
    "slug": "shoes",
    "brandCount": 102
  },
  {
    "name": "Food, Drinks & Restaurants",
    "slug": "food-drinks-and-restaurants",
    "brandCount": 85
  },
  {
    "name": "Auto & Tires",
    "slug": "auto-and-tires",
    "brandCount": 67
  },
  {
    "name": "Subscription Boxes & Services",
    "slug": "subscription-boxes-and-services",
    "brandCount": 57
  },
  {
    "name": "Events & Entertainment",
    "slug": "events-and-entertainment",
    "brandCount": 55
  },
  {
    "name": "Toys & Games",
    "slug": "toys-and-games",
    "brandCount": 49
  },
  {
    "name": "Gifts, Flowers & Parties",
    "slug": "gifts-flowers-and-parties",
    "brandCount": 38
  },
  {
    "name": "Pets",
    "slug": "pets",
    "brandCount": 37
  },
  {
    "name": "Office Supplies",
    "slug": "office-supplies",
    "brandCount": 28
  },
  {
    "name": "Baby & Toddler",
    "slug": "baby-and-toddler",
    "brandCount": 25
  }
]